flex/__init__.py
flex/cli.py
flex/constants.py
flex/context_managers.py
flex/core.py
flex/datastructures.py
flex/decorators.py
flex/error_messages.py
flex/exceptions.py
flex/formats.py
flex/functional.py
flex/http.py
flex/parameters.py
flex/paths.py
flex/utils.py
flex/compat/__init__.py
flex/compat/validate_email.py
flex/loading/__init__.py
flex/loading/common/__init__.py
flex/loading/common/default.py
flex/loading/common/enum.py
flex/loading/common/external_docs.py
flex/loading/common/format.py
flex/loading/common/max_items.py
flex/loading/common/max_length.py
flex/loading/common/maximum.py
flex/loading/common/mimetypes.py
flex/loading/common/min_items.py
flex/loading/common/min_length.py
flex/loading/common/minimum.py
flex/loading/common/multiple_of.py
flex/loading/common/pattern.py
flex/loading/common/reference.py
flex/loading/common/required.py
flex/loading/common/unique_items.py
flex/loading/common/schema/__init__.py
flex/loading/common/schema/max_properties.py
flex/loading/common/schema/min_properties.py
flex/loading/common/schema/read_only.py
flex/loading/common/schema/required.py
flex/loading/common/schema/title.py
flex/loading/common/schema/type.py
flex/loading/common/single_header/__init__.py
flex/loading/common/single_header/collection_format.py
flex/loading/common/single_header/description.py
flex/loading/common/single_header/type.py
flex/loading/common/single_parameter/__init__.py
flex/loading/common/single_parameter/collection_format.py
flex/loading/common/single_parameter/description.py
flex/loading/common/single_parameter/in_.py
flex/loading/common/single_parameter/items.py
flex/loading/common/single_parameter/name.py
flex/loading/common/single_parameter/type.py
flex/loading/definitions/__init__.py
flex/loading/definitions/schema_definitions.py
flex/loading/definitions/parameters/__init__.py
flex/loading/definitions/parameters/single.py
flex/loading/definitions/responses/__init__.py
flex/loading/definitions/responses/single/__init__.py
flex-6.14.0.dist-info/LICENSE
flex-6.14.0.dist-info/METADATA
flex-6.14.0.dist-info/WHEEL
flex-6.14.0.dist-info/entry_points.txt
flex-6.14.0.dist-info/top_level.txt
flex-6.14.0.dist-info/RECORD
