Metadata-Version: 2.1
Name: flex
Version: 6.14.0
Summary: Swagger Schema validation.
Home-page: https://github.com/pipermerriam/flex
Author: Piper Merriam
Author-email: pipermerriam@gmail.com
License: BSD
Keywords: rest swagger
Platform: UNKNOWN
Classifier: Intended Audience :: Developers
Classifier: License :: OSI Approved :: BSD License
Classifier: Natural Language :: English
Classifier: Programming Language :: Python :: 2
Classifier: Programming Language :: Python :: 2.7
Classifier: Programming Language :: Python :: 3
Classifier: Programming Language :: Python :: 3.3
Classifier: Programming Language :: Python :: 3.4
Classifier: Programming Language :: Python :: 3.5
Classifier: Programming Language :: Python :: 3.6
